setup.cfg
setup.py
EyeTrackFatigue.egg-info/PKG-INFO
EyeTrackFatigue.egg-info/SOURCES.txt
EyeTrackFatigue.egg-info/dependency_links.txt
EyeTrackFatigue.egg-info/requires.txt
EyeTrackFatigue.egg-info/top_level.txt
EyeTrackFatigue/Analise/GeoMetrics.py
EyeTrackFatigue/Analise/Movements.py
EyeTrackFatigue/Analise/Names.py
EyeTrackFatigue/Analise/ParsedData.py
EyeTrackFatigue/Analise/SecondaryMetrics.py
EyeTrackFatigue/Analise/__init__.py
EyeTrackFatigue/DeviceManager/DeviceHandler.py
EyeTrackFatigue/DeviceManager/Synchronizer.py
EyeTrackFatigue/DeviceManager/__init__.py
EyeTrackFatigue/Evaluate/BasicEval.py
EyeTrackFatigue/Evaluate/DecisionTreeEval.py
EyeTrackFatigue/Evaluate/Evaluator.py
EyeTrackFatigue/Evaluate/HybridEval.py
EyeTrackFatigue/Evaluate/MLPEval.py
EyeTrackFatigue/Evaluate/RandomForestEval.py
EyeTrackFatigue/Evaluate/__init__.py
EyeTrackFatigue/Input/InputSection.py
EyeTrackFatigue/Input/SingleData.py
EyeTrackFatigue/Input/__init__.py
EyeTrackFatigue/Meta/EventTests.py
EyeTrackFatigue/Meta/Time_Test.py
EyeTrackFatigue/Meta/UnitTests.py
EyeTrackFatigue/Meta/videoProcessorAlpha.py
EyeTrackFatigue/UI/DataGather.py
EyeTrackFatigue/UI/EvalApp.py